grailkit/__init__.py
grailkit/bible.py
grailkit/bible_parse.py
grailkit/core.py
grailkit/db.py
grailkit/dna.py
grailkit/osc.py
grailkit/plug.py
grailkit/util.py
grailkit-0.10.1.dist-info/LICENSE
grailkit-0.10.1.dist-info/METADATA
grailkit-0.10.1.dist-info/WHEEL
grailkit-0.10.1.dist-info/top_level.txt
grailkit-0.10.1.dist-info/RECORD
